imbot/__init__.py
imbot/imbotmsgs.py
imbot/imbotversion.py
imbot-0.1.8.dist-info/LICENSE
imbot-0.1.8.dist-info/METADATA
imbot-0.1.8.dist-info/WHEEL
imbot-0.1.8.dist-info/top_level.txt
imbot-0.1.8.dist-info/RECORD
