Metadata-Version: 2.1
Name: imbot
Version: 0.1.8
Summary: imbot - create a bot to control any website.
Home-page: UNKNOWN
Author: yasserbdj96
Author-email: yasser.bdj96@gmail.com
License: Apache Software License
Project-URL: Source, https://github.com/yasserbdj96/imbot
Project-URL: WebSite, https://yasserbdj96.github.io/imbot
Project-URL: Chat, https://gitter.im/yasserbdj96/imbot
Project-URL: Author WebSite, https://yasserbdj96.github.io/
Keywords: yasserbdj96,python,bot,website bot,robot
Platform: UNKNOWN
Classifier: Environment :: Web Environment
Classifier: Development Status :: 5 - Production/Stable
Classifier: Intended Audience :: Developers
Classifier: Natural Language :: English
Classifier: License :: OSI Approved :: Apache Software License
Classifier: Programming Language :: Python
Classifier: Programming Language :: Python :: 3
Classifier: Programming Language :: Python :: 3.7
Classifier: Programming Language :: Python :: 3.8
Classifier: Programming Language :: Python :: 3.9
Classifier: Programming Language :: Python :: 3.10
Classifier: Programming Language :: Python :: 3 :: Only
Classifier: Operating System :: Unix
Classifier: Operating System :: MacOS :: MacOS X
Classifier: Operating System :: Microsoft :: Windows
Classifier: Topic :: Software Development :: Build Tools
Classifier: Topic :: Software Development :: Libraries
Classifier: Topic :: Software Development :: Libraries :: Python Modules
Classifier: Topic :: Internet :: WWW/HTTP
Requires-Python: >=3.x.x
License-File: LICENSE
Requires-Dist: selenium
Requires-Dist: hexor
Requires-Dist: asciitext
